LICENSE
MANIFEST.in
README.md
setup.py
netsnmp/__init__.py
netsnmp/__main__.py
netsnmp/_api.c
netsnmp/_api.h
netsnmp/_hex.py
netsnmp/get.c
netsnmp/get_async.c
netsnmp/interface.c
netsnmp/session.c
netsnmp/_dev/__init__.py
netsnmp/_dev/arris.py
netsnmp/_dev/cisco.py
netsnmp/_dev/technicolor.py
netsnmp_py.egg-info/PKG-INFO
netsnmp_py.egg-info/SOURCES.txt
netsnmp_py.egg-info/dependency_links.txt
netsnmp_py.egg-info/top_level.txt