Metadata-Version: 2.1
Name: netsnmp-py
Version: 0.6
Summary: Python NET-SNMP Bindings
Home-page: https://github.com/xstaticxgpx/netsnmp-py3
Download-URL: https://github.com/xstaticxgpx/netsnmp-py3/archive/v0.6.tar.gz
Author: Gabe Pacuilla
Author-email: root@un1x.su
License: MIT License
Classifier: Development Status :: 3 - Alpha
Classifier: Intended Audience :: Developers
Classifier: License :: OSI Approved :: MIT License
Classifier: Operating System :: POSIX
Classifier: Programming Language :: C
Classifier: Programming Language :: Python :: 2.7
Classifier: Programming Language :: Python :: 3
Classifier: Topic :: Software Development :: Libraries
License-File: LICENSE
